emotiva_rs232/__about__.py
emotiva_rs232/__init__.py
emotiva_rs232/const.py
emotiva_rs232/emotiva_device.py
emotiva_rs232/fusion_flex.py
emotiva_rs232-0.0.3.dist-info/METADATA
emotiva_rs232-0.0.3.dist-info/WHEEL
emotiva_rs232-0.0.3.dist-info/licenses/LICENSE
emotiva_rs232-0.0.3.dist-info/RECORD
